hype/__init__.py
hype/function.py
hype/tools/__init__.py
hype/tools/anthropic.py
hype/tools/ollama.py
hype/tools/openai.py
hype_up-0.0.1.dist-info/METADATA
hype_up-0.0.1.dist-info/WHEEL
hype_up-0.0.1.dist-info/licenses/LICENSE.md
hype_up-0.0.1.dist-info/RECORD
