Metadata-Version: 2.3
Name: hype-up
Version: 0.0.1
License-File: LICENSE.md
Requires-Python: >=3.10
Requires-Dist: docstring-parser>=0.16
Requires-Dist: pydantic>=2.0
Provides-Extra: testing
Requires-Dist: pytest; extra == 'testing'
